wids_datathon_2020/__init__.py
wids_datathon_2020/inference.py
wids_datathon_2020/learn.py
wids_datathon_2020/data/__init__.py
wids_datathon_2020/data/encode_dataset.py
wids_datathon_2020/data/make_dataset.py
wids_datathon_2020/data/stratify_dataset.py
wids_datathon_2020/data/unzip_dataset.py
wids_datathon_2020/features/__init__.py
wids_datathon_2020/features/build_features copy.py
wids_datathon_2020/features/build_features.py
wids_datathon_2020/models/__init__.py
wids_datathon_2020/models/predict_model.py
wids_datathon_2020/models/train_model.py
wids_datathon_2020/visualization/__init__.py
wids_datathon_2020/visualization/visualize.py
wids_datathon_2020-0.1.5.dist-info/LICENSE
wids_datathon_2020-0.1.5.dist-info/METADATA
wids_datathon_2020-0.1.5.dist-info/WHEEL
wids_datathon_2020-0.1.5.dist-info/top_level.txt
wids_datathon_2020-0.1.5.dist-info/RECORD
