Metadata-Version: 2.1
Name: wids-datathon-2020
Version: 0.1.5
Summary: The challenge is to create a model that uses data from the first 24 hours of intensive care to predict patient survival. (Kaggle Proj) https://www.kaggle.com/c/widsdatathon2020/overview
Home-page: https://github.com/iainwo/kaggle/tree/master/wids-datathon-2020
Author: Iain Wong
Author-email: iainwong@outlook.com
License: MIT
Platform: UNKNOWN
Classifier: Programming Language :: Python :: 3
Classifier: License :: OSI Approved :: MIT License
Classifier: Operating System :: OS Independent
Requires-Python: >=3.6
Requires-Dist: pandas
Requires-Dist: python-dotenv
Requires-Dist: Click
Requires-Dist: pyarrow
Requires-Dist: numpy
Requires-Dist: scikit-learn
